beetlesafari/__init__.py
beetlesafari/io/__init__.py
beetlesafari/io/_clearcontrol_dataset.py
beetlesafari/io/_clearcontrol_dataset_dock_widget.py
beetlesafari/io/_imread_raw.py
beetlesafari/io/_imread_raw_folder.py
beetlesafari/io/_imread_zip.py
beetlesafari/utils/__init__.py
beetlesafari/utils/_filenames.py
beetlesafari/utils/_stopwatch.py
beetlesafari/utils/_time.py
beetlesafari-0.4.0.dist-info/LICENSE
beetlesafari-0.4.0.dist-info/METADATA
beetlesafari-0.4.0.dist-info/WHEEL
beetlesafari-0.4.0.dist-info/entry_points.txt
beetlesafari-0.4.0.dist-info/top_level.txt
beetlesafari-0.4.0.dist-info/RECORD
