Metadata-Version: 2.1
Name: beetlesafari
Version: 0.4.0
Summary: A napari plugin for loading and working with light sheet imaging data of developing embryos acquired using ClearControl, e.g. _Tribolium castaneum_.
Home-page: https://github.com/haesleinhuepf/beetlesafari
Author: Robert Haase
Author-email: robert.haase@tu-dresden.de
Classifier: Programming Language :: Python :: 3
Classifier: License :: OSI Approved :: BSD License
Classifier: Operating System :: OS Independent
Classifier: Framework :: napari
Classifier: Intended Audience :: Science/Research
Classifier: Development Status :: 3 - Alpha
Requires-Python: >=3.7
License-File: LICENSE
Requires-Dist: numpy
Requires-Dist: pyopencl
Requires-Dist: toolz
Requires-Dist: scikit-image
Requires-Dist: requests
Requires-Dist: pyclesperanto-prototype
Requires-Dist: napari
Requires-Dist: magicgui
Requires-Dist: dask
Requires-Dist: cachetools
Requires-Dist: napari-tools-menu
